{
  "notes": [
    {
      "noteType": "url",
      "title": {
        "en": "exercise execution",
        "fr": "exercise execution"
      },
      "url": "https://videos.pexels.com/video-files/35735258/15146155_2560_1440_30fps.mp4"
    },
    {
      "noteType": "description",
      "title": {
        "en": "setup",
        "fr": "setup"
      },
      "description": {
        "en": "Hinge the torso to about 45-90°, dumbbells hanging below you, palms facing each other. Lift your arms out to the sides in an arc, elbows slightly bent, to shoulder height. Squeeze the rear delts and mid-back at the top. Lower slowly. Can be done seated, bent over a bench.",
        "fr": "Penchez le buste à environ 45-90°, haltères pendants sous vous, paumes se faisant face. Levez les bras sur les côtés en arc de cercle, coudes légèrement fléchis, jusqu'à hauteur des épaules. Contractez les deltoïdes postérieurs et le milieu du dos en haut. Descendez lentement. Peut se faire assis, penché sur un banc."
      }
    }
  ]
}