{
  "notes": [
    {
      "noteType": "media",
      "title": {
        "en": "exercise execution",
        "fr": "exercise execution"
      },
      "mediaUri": "media/exercise-execution.mp4",
      "mediaType": "video"
    },
    {
      "noteType": "description",
      "title": {
        "en": "setup",
        "fr": "setup"
      },
      "description": {
        "en": "Lying on your back, hands under the glutes or at your sides for support. Legs straight or slightly bent. Raise the legs to vertical while contracting the lower abs. Lower slowly without letting the feet touch the floor. Can also be performed hanging from a bar.",
        "fr": "Allongé sur le dos, mains sous les fessiers ou le long du corps pour soutien. Jambes tendues ou légèrement fléchies. Levez les jambes jusqu'à la verticale en contractant les abdominaux inférieurs. Descendez lentement sans laisser les pieds toucher le sol. Peut se faire en suspension à la barre."
      }
    }
  ]
}